{
    "Tokens": {
        "correct": 662,
        "gold_total": 662,
        "system_total": 662,
        "aligned_total": null,
        "precision": 1.0,
        "recall": 1.0,
        "f1": 1.0,
        "aligned_accuracy": null
    },
    "Sentences": {
        "correct": 131,
        "gold_total": 131,
        "system_total": 131,
        "aligned_total": null,
        "precision": 1.0,
        "recall": 1.0,
        "f1": 1.0,
        "aligned_accuracy": null
    },
    "Words": {
        "correct": 662,
        "gold_total": 662,
        "system_total": 662,
        "aligned_total": null,
        "precision": 1.0,
        "recall": 1.0,
        "f1": 1.0,
        "aligned_accuracy": null
    },
    "UPOS": {
        "correct": 0,
        "gold_total": 662,
        "system_total": 662,
        "aligned_total": 662,
        "precision": 0.0,
        "recall": 0.0,
        "f1": 0.0,
        "aligned_accuracy": 0.0
    },
    "XPOS": {
        "correct": 0,
        "gold_total": 662,
        "system_total": 662,
        "aligned_total": 662,
        "precision": 0.0,
        "recall": 0.0,
        "f1": 0.0,
        "aligned_accuracy": 0.0
    },
    "UFeats": {
        "correct": 652,
        "gold_total": 662,
        "system_total": 662,
        "aligned_total": 662,
        "precision": 0.9848942598187311,
        "recall": 0.9848942598187311,
        "f1": 0.9848942598187311,
        "aligned_accuracy": 0.9848942598187311
    },
    "AllTags": {
        "correct": 0,
        "gold_total": 662,
        "system_total": 662,
        "aligned_total": 662,
        "precision": 0.0,
        "recall": 0.0,
        "f1": 0.0,
        "aligned_accuracy": 0.0
    },
    "Lemmas": {
        "correct": 662,
        "gold_total": 662,
        "system_total": 662,
        "aligned_total": 662,
        "precision": 1.0,
        "recall": 1.0,
        "f1": 1.0,
        "aligned_accuracy": 1.0
    },
    "UAS": {
        "correct": 537,
        "gold_total": 662,
        "system_total": 662,
        "aligned_total": 662,
        "precision": 0.8111782477341389,
        "recall": 0.8111782477341389,
        "f1": 0.8111782477341389,
        "aligned_accuracy": 0.8111782477341389
    },
    "LAS": {
        "correct": 70,
        "gold_total": 662,
        "system_total": 662,
        "aligned_total": 662,
        "precision": 0.10574018126888217,
        "recall": 0.10574018126888217,
        "f1": 0.10574018126888217,
        "aligned_accuracy": 0.10574018126888217
    },
    "CLAS": {
        "correct": 69,
        "gold_total": 491,
        "system_total": 480,
        "aligned_total": 491,
        "precision": 0.14375,
        "recall": 0.14052953156822812,
        "f1": 0.14212152420185376,
        "aligned_accuracy": 0.14052953156822812
    },
    "MLAS": {
        "correct": 0,
        "gold_total": 491,
        "system_total": 480,
        "aligned_total": 491,
        "precision": 0.0,
        "recall": 0.0,
        "f1": 0.0,
        "aligned_accuracy": 0.0
    },
    "BLEX": {
        "correct": 69,
        "gold_total": 491,
        "system_total": 480,
        "aligned_total": 491,
        "precision": 0.14375,
        "recall": 0.14052953156822812,
        "f1": 0.14212152420185376,
        "aligned_accuracy": 0.14052953156822812
    }
}